main.py
pygame_widget_kit/Button.py
pygame_widget_kit/Radio.py
pygame_widget_kit/Select.py
pygame_widget_kit/Slider.py
pygame_widget_kit/Text.py
pygame_widget_kit/TextArea.py
pygame_widget_kit/TextInput.py
pygame_widget_kit/UIComponent.py
pygame_widget_kit/UIManager.py
pygame_widget_kit/Widget.py
pygame_widget_kit/__init__.py
pygame_widget_kit-0.0.5.dist-info/licenses/LICENSE
pygame_widget_kit-0.0.5.dist-info/METADATA
pygame_widget_kit-0.0.5.dist-info/WHEEL
pygame_widget_kit-0.0.5.dist-info/top_level.txt
pygame_widget_kit-0.0.5.dist-info/RECORD
